izienv/__init__.py
izienv/_base_env.py
izienv/_checkers.py
izienv/_load_izienv.py
izienv-0.1.2.dist-info/LICENSE
izienv-0.1.2.dist-info/METADATA
izienv-0.1.2.dist-info/WHEEL
izienv-0.1.2.dist-info/top_level.txt
izienv-0.1.2.dist-info/RECORD
