Metadata-Version: 2.1
Name: izienv
Version: 0.1.2
Summary: Python package to handle multiple files with environment variables.
Home-page: https://pypi.org/project/izienv/
Author: Alejo Prieto Dávalos
Author-email: alejoprietodavalos@gmail.com
Project-URL: Source, https://github.com/AlejoPrietoDavalos/izienv/
Requires-Python: >=3.11
License-File: LICENSE
Requires-Dist: python-dotenv >=1.0.1
